john_toolbox/__init__.py
john_toolbox/evaluation/metrics.py
john_toolbox/evaluation/visualisation.py
john_toolbox/preprocessing/__init__.py
john_toolbox/preprocessing/pandas_pipeline.py
john_toolbox/preprocessing/pandas_transformers.py
john_toolbox/preprocessing/utils.py
john_toolbox/tutorial/binary/xgboost/preprocessing.py
john_toolbox/tutorial/binary/xgboost/tuning.py
john_toolbox/utils/__init__.py
john_toolbox/utils/color_formatter.py
john_toolbox/utils/logger_config.py
john_toolbox/utils/logging.json
john_toolbox/utils/logging_dev.json
john_toolbox-0.5.1.dist-info/WHEEL
john_toolbox-0.5.1.dist-info/METADATA
john_toolbox-0.5.1.dist-info/RECORD
