Metadata-Version: 2.1
Name: john-toolbox
Version: 0.5.1
Summary: Wrapper for transformers scikit learn pipeline and wrapper for ml model
Home-page: https://github.com/nguyenanht/john-toolbox
License: MIT
Keywords: sklearn,pipeline,pytorch
Author: john
Author-email: contact@nguyenjohnathan.com
Requires-Python: >=3.8,<3.10
Classifier: License :: OSI Approved :: MIT License
Classifier: Programming Language :: Python :: 3
Classifier: Programming Language :: Python :: 3.8
Classifier: Programming Language :: Python :: 3.9
Requires-Dist: Jinja2 (>=2.11.0,<3.0.0)
Requires-Dist: MarkupSafe (==2.0.1)
Requires-Dist: numpy (>=1.19,<2.0)
Requires-Dist: pandas (>=1.1,<2.0)
Requires-Dist: tqdm (>=4.51,<5.0)
Project-URL: Repository, https://github.com/nguyenanht/john-toolbox
